compario/__init__.py
compario/main.py
compario/prompts.py
compario-2025.12.21102846.dist-info/METADATA
compario-2025.12.21102846.dist-info/WHEEL
compario-2025.12.21102846.dist-info/top_level.txt
compario-2025.12.21102846.dist-info/RECORD
