Metadata-Version: 2.4
Name: compario
Version: 2025.12.21102846
Summary: A new package that uses large language models and pattern matching to perform structured similarity comparisons between textual content based on normalized compression distance. Users provide multiple
Author-email: compario <hi@eugene.plus>
License: MIT
Project-URL: Homepage, https://github.com/chigwell/compario
Requires-Python: >=3.9
Requires-Dist: langchain-llm7>=0.0.0
Requires-Dist: llmatch-messages>=0.0.0
Requires-Dist: langchain-core>=0.3.0
